kronos_backtester/Backtester.py
kronos_backtester/__init__.py
kronos_backtester-0.1.2.dist-info/METADATA
kronos_backtester-0.1.2.dist-info/WHEEL
kronos_backtester-0.1.2.dist-info/licenses/LICENSE
kronos_backtester-0.1.2.dist-info/RECORD
