Metadata-Version: 2.1
Name: kronos_backtester
Version: 0.1.2
Summary: A backtesting framework for the trading strategies developed by Quant Illinois.
Project-URL: Homepage, https://https://github.com/quantillinois/kronos
Project-URL: Bug Tracker, https://https://github.com/quantillinois/kronos/issues
Author-email: Quant Illinois <quant.illinois@gmail.com>
License-File: LICENSE
Classifier: License :: OSI Approved :: MIT License
Classifier: Operating System :: OS Independent
Classifier: Programming Language :: Python :: 3
Requires-Python: >=3.7.1
Requires-Dist: pandas>=1.3.0
Requires-Dist: plotly>=5.18.0
Requires-Dist: yfinance
